pymcache_fdw-0.2.0.dist-info/DESCRIPTION.rst
pymcache_fdw-0.2.0.dist-info/top_level.txt
pymcache_fdw-0.2.0.dist-info/WHEEL
pymcache_fdw-0.2.0.dist-info/metadata.json
pymcache_fdw-0.2.0.dist-info/RECORD
pymcache_fdw-0.2.0.dist-info/METADATA
pymcache_fdw/utils.py
pymcache_fdw/__init__.py
pymcache_fdw/defaults.py
