Metadata-Version: 2.0
Name: pymcache-fdw
Version: 0.2.0
Summary: memcache fdw for postgresql
Home-page: https://bitbucket.org/olshevskiy87/pymcache_fdw
Author: Dmitriy Olshevskiy
Author-email: olshevskiy87@bk.ru
License: MIT
Keywords: memcache postgres pgsql fdw wrapper
Platform: UNKNOWN
Requires-Dist: pymemcache
